agent_data_toolkit/__init__.py
agent_data_toolkit/_version.py
agent_data_toolkit/py.typed
agent_data_toolkit/postgresql/__init__.py
agent_data_toolkit/postgresql/client.py
agent_data_toolkit/postgresql/connection.py
agent_data_toolkit/postgresql/io.py
agent_data_toolkit/postgresql/queries.py
agent_data_toolkit/postgresql/schema.py
agent_data_toolkit/postgresql/sql.py
agent_data_toolkit-0.1.2.dist-info/licenses/LICENSE
agent_data_toolkit-0.1.2.dist-info/METADATA
agent_data_toolkit-0.1.2.dist-info/WHEEL
agent_data_toolkit-0.1.2.dist-info/top_level.txt
agent_data_toolkit-0.1.2.dist-info/RECORD
