Metadata-Version: 2.4
Name: agent-data-toolkit
Version: 0.1.2
Summary: Connect agents to data
Author-email: Roberto Rodriguez <9653181+Cyb3rWard0g@users.noreply.github.com>
License: Apache-2.0
Project-URL: Homepage, https://github.com/Cyb3rWard0g/agent-data-toolkit
Project-URL: Issues, https://github.com/Cyb3rWard0g/agent-data-toolkit/issues
Classifier: License :: OSI Approved :: Apache Software License
Classifier: Programming Language :: Python :: 3
Classifier: Programming Language :: Python :: 3.11
Classifier: Programming Language :: Python :: 3.12
Classifier: Programming Language :: Python :: 3.13
Requires-Python: <3.14,>=3.11
License-File: LICENSE
Requires-Dist: pandas>=2.3.3
Provides-Extra: dev
Requires-Dist: pytest>=8.4.2; extra == "dev"
Requires-Dist: pytest-asyncio>=0.23; extra == "dev"
Requires-Dist: ruff; extra == "dev"
Requires-Dist: black; extra == "dev"
Requires-Dist: anyio>=4; extra == "dev"
Requires-Dist: build; extra == "dev"
Requires-Dist: twine; extra == "dev"
Requires-Dist: packaging; extra == "dev"
Requires-Dist: setuptools; extra == "dev"
Requires-Dist: setuptools_scm; extra == "dev"
Requires-Dist: wheel; extra == "dev"
Provides-Extra: postgresql
Requires-Dist: psycopg[binary]>=3.2.10; extra == "postgresql"
Requires-Dist: psycopg_pool>=3.2.6; extra == "postgresql"
Requires-Dist: pyarrow>=21.0.0; extra == "postgresql"
Provides-Extra: all
Requires-Dist: agent-data-toolkit[postgresql]; extra == "all"
Dynamic: license-file
